{
  "generated_at": "2026-07-12T08:00:46.319737+00:00",
  "total_articles": 45,
  "sources_fetched": 8,
  "sources_failed": 7,
  "editors_pick": {
    "id": "87510afbbfbf",
    "title": "Don’t Overlook Hell’s Evangelistic Appeal",
    "summary": "Humanity was created good, but we currently live in a fallen world. We shouldn’t be surprised when bad people do bad things.",
    "url": "https://www.thegospelcoalition.org/article/hell-evangelistic-appeal/",
    "source_name": "The Gospel Coalition",
    "author": "Sean Nolan",
    "topic": "faith",
    "score": 78,
    "read_time": "1 min",
    "published_at": "2026-07-12T04:00:00+00:00",
    "scraped_at": "2026-07-12T08:00:28.212314+00:00",
    "trust_tier": 1,
    "is_live": true,
    "is_editors_pick": true,
    "time_ago": "4h ago"
  },
  "articles": [
    {
      "id": "87510afbbfbf",
      "title": "Don’t Overlook Hell’s Evangelistic Appeal",
      "summary": "Humanity was created good, but we currently live in a fallen world. We shouldn’t be surprised when bad people do bad things.",
      "url": "https://www.thegospelcoalition.org/article/hell-evangelistic-appeal/",
      "source_name": "The Gospel Coalition",
      "author": "Sean Nolan",
      "topic": "faith",
      "score": 78,
      "read_time": "1 min",
      "published_at": "2026-07-12T04:00:00+00:00",
      "scraped_at": "2026-07-12T08:00:28.212314+00:00",
      "trust_tier": 1,
      "is_live": true,
      "is_editors_pick": true,
      "time_ago": "4h ago"
    },
    {
      "id": "29cb88afd2cb",
      "title": "Recapitulation: What It Is and Why It Will Help You Endure",
      "summary": "Our daily repetitions matter. ‘Agains’ are an invitation to remember what God has done and what God will do.",
      "url": "https://www.thegospelcoalition.org/article/recapitulation-what-and-why/",
      "source_name": "The Gospel Coalition",
      "author": "Samantha Decker",
      "topic": "faith",
      "score": 59,
      "read_time": "1 min",
      "published_at": "2026-07-11T04:00:00+00:00",
      "scraped_at": "2026-07-12T08:00:28.212409+00:00",
      "trust_tier": 1,
      "is_live": true,
      "is_editors_pick": false,
      "time_ago": "yesterday"
    },
    {
      "id": "aaac4bd1d3b3",
      "title": "Editor’s Picks: New Bible Study Curricula",
      "summary": "Ten recently published Bible study curricula for individuals or small groups.",
      "url": "https://www.thegospelcoalition.org/reviews/editors-picks-curricula-summer-2026/",
      "source_name": "The Gospel Coalition",
      "author": "Andrew Spencer",
      "topic": "faith",
      "score": 45,
      "read_time": "1 min",
      "published_at": "2026-07-10T04:02:00+00:00",
      "scraped_at": "2026-07-12T08:00:28.212543+00:00",
      "trust_tier": 1,
      "is_live": true,
      "is_editors_pick": false,
      "time_ago": "2d ago"
    },
    {
      "id": "a03fc3f0fef2",
      "title": "Iran and the US Agree on Little, Except to Not Talk About Religious Freedom",
      "summary": "This week, as Iranians thronged for the delayed funeral of Supreme Leader Ali Khamenei and their government resumed trading airstrikes with the United States, a fragile cease-fire between the two countries crumbled—the latest turn in a conflict entering its fifth month with no clear end in sight....",
      "url": "https://www.christianitytoday.com/2026/07/iran-us-deal-persecution-christians/",
      "source_name": "Christianity Today",
      "author": "Harvest Prude",
      "topic": "grief",
      "score": 44,
      "read_time": "1 min",
      "published_at": "2026-07-09T17:50:40+00:00",
      "scraped_at": "2026-07-12T08:00:28.337129+00:00",
      "trust_tier": 1,
      "is_live": true,
      "is_editors_pick": false,
      "time_ago": "2d ago"
    },
    {
      "id": "27a2358aa150",
      "title": "God’s Kingdom Is Alive, Even in the Midst of Setbacks",
      "summary": "Throughout Mario Kasih’s life and ministry, Christianity Today has been a source of inspiration to grow closer to God and to other members and ministers of the global church. Mario started reading Christianity Today after the Lausanne Conference in 2024, when he was a virtual attendee and given a...",
      "url": "https://www.christianitytoday.com/about/stories/gods-kingdom-is-alive-even-in-the-midst-of-setbacks/",
      "source_name": "Christianity Today",
      "author": "Anne Kerhoulas",
      "topic": "faith",
      "score": 44,
      "read_time": "1 min",
      "published_at": "2026-07-09T14:39:38+00:00",
      "scraped_at": "2026-07-12T08:00:28.337246+00:00",
      "trust_tier": 1,
      "is_live": true,
      "is_editors_pick": false,
      "time_ago": "2d ago"
    },
    {
      "id": "deac65c809bb",
      "title": "Christopher Nolan’s ‘Odyssey’ and Homer’s Splintered Gospel",
      "summary": "Centuries before the New Testament authors wrote their gospels, Homer laid down his own evangelium: Now royal Odysseus, who had borne the long war, spoke again: …“Your lord is now at hand.And I expect a gift for this good news [evangelion]when he enters his own hall. Till then I would nottake a r...",
      "url": "https://www.christianitytoday.com/2026/07/will-nolans-odyssey-live-up-to-homers-splintered-gospel/",
      "source_name": "Christianity Today",
      "author": "Haley Byrd Wilt",
      "topic": "faith",
      "score": 44,
      "read_time": "1 min",
      "published_at": "2026-07-09T10:00:00+00:00",
      "scraped_at": "2026-07-12T08:00:28.337356+00:00",
      "trust_tier": 1,
      "is_live": true,
      "is_editors_pick": false,
      "time_ago": "2d ago"
    },
    {
      "id": "abdd53342146",
      "title": "After US Aid Cuts, the Sick Wonder Who Will Visit Them",
      "summary": "Florence Mwendwa, 49, proudly showed off her walker as she took unsteady steps up a rocky path surrounded by tea farms in rural Kenya. Her husband, Ashford Mutwiri, helped her walk, but the health workers who visit her regularly at home told her she was looking so much better than a few months ag...",
      "url": "https://www.christianitytoday.com/2026/07/hiv-pepfar-usaid-cuts-trump-humanitarian-aid-mission-hospitals/",
      "source_name": "Christianity Today",
      "author": "Emily Belz",
      "topic": "marriage",
      "score": 44,
      "read_time": "1 min",
      "published_at": "2026-07-09T10:00:00+00:00",
      "scraped_at": "2026-07-12T08:00:28.337542+00:00",
      "trust_tier": 1,
      "is_live": true,
      "is_editors_pick": false,
      "time_ago": "2d ago"
    },
    {
      "id": "a023b8d10606",
      "title": "Mindfulness Will Never Be Enough",
      "summary": "As this summer started, I slipped into spiritual sleepiness. For the last nine months of the school year, I’d served as editor for my college newspaper, vice president for a club, and a residence life leader, all while working several part-time jobs. In my exhaustion, God sustained me through the...",
      "url": "https://www.christianitytoday.com/2026/07/mindfulness-will-never-be-enough/",
      "source_name": "Christianity Today",
      "author": "Kate Lucky",
      "topic": "faith",
      "score": 43,
      "read_time": "1 min",
      "published_at": "2026-07-10T10:00:00+00:00",
      "scraped_at": "2026-07-12T08:00:28.336867+00:00",
      "trust_tier": 1,
      "is_live": true,
      "is_editors_pick": false,
      "time_ago": "yesterday"
    },
    {
      "id": "93e853e78f51",
      "title": "A New Way to Think About Women’s Roles",
      "summary": "This piece was adapted from CT’s books newsletter. Subscribe here. Julia Higgins, Christ and His Bride: How Men and Women Tell the Story of the Gospel (B&#38;H Books, 2026) “In the past thirty years or so, conversations about womanhood in the church have been low-key obsessed with what women shou...",
      "url": "https://www.christianitytoday.com/2026/07/new-way-women-church-complementarianism-review/",
      "source_name": "Christianity Today",
      "author": "tberglund@christianitytoday.com",
      "topic": "faith",
      "score": 43,
      "read_time": "1 min",
      "published_at": "2026-07-10T10:00:00+00:00",
      "scraped_at": "2026-07-12T08:00:28.336987+00:00",
      "trust_tier": 1,
      "is_live": true,
      "is_editors_pick": false,
      "time_ago": "yesterday"
    },
    {
      "id": "e380d3ececde",
      "title": "Died: Robert Sloan",
      "summary": "Robert Sloan Jr., president of Houston Christian University, suffered a massive stroke and died on July 4 at age 77. Sloan played baseball as a Baylor University undergraduate in the late 1960s and was president of the university from 1995 to 2005. Southwestern Baptist Theological Seminary presid...",
      "url": "https://www.christianitytoday.com/2026/07/died-robert-sloan/",
      "source_name": "Christianity Today",
      "author": "Mia Staub",
      "topic": "faith",
      "score": 42,
      "read_time": "1 min",
      "published_at": "2026-07-09T10:00:00+00:00",
      "scraped_at": "2026-07-12T08:00:28.337634+00:00",
      "trust_tier": 1,
      "is_live": true,
      "is_editors_pick": false,
      "time_ago": "2d ago"
    },
    {
      "id": "eaff503a4ade",
      "title": "7 Signs Your Church Is Dying (Even If Attendance Looks Fine)",
      "summary": "No pastor wakes up and decides the church is dying. It happens in the silences between sermons. In the conversations nobody starts. In the numbers nobody wants to pull up on a screen. A dying church isn&#8217;t always the one with a half empty parking lot. Sometimes it&#8217;s the church that sti...",
      "url": "https://churchleaders.com/pastors/2217233-church-slowly-dying-signs.html",
      "source_name": "Church Leaders",
      "author": "David Mercer",
      "topic": "leadership",
      "score": 42,
      "read_time": "1 min",
      "published_at": "2026-07-10T18:51:18+00:00",
      "scraped_at": "2026-07-12T08:00:36.239761+00:00",
      "trust_tier": 2,
      "is_live": true,
      "is_editors_pick": false,
      "time_ago": "yesterday"
    },
    {
      "id": "6b9f837193e6",
      "title": "12 Jul 2026",
      "summary": "",
      "url": "https://dewsofhope.ca/12-july-2026/",
      "source_name": "Daily Dews of Hope",
      "author": "DD0H",
      "topic": "devotional",
      "score": 42,
      "read_time": "3 min",
      "published_at": "2026-07-12T04:00:41+00:00",
      "scraped_at": "2026-07-12T08:00:42.800956+00:00",
      "trust_tier": 3,
      "is_live": true,
      "is_editors_pick": false,
      "time_ago": "4h ago"
    },
    {
      "id": "791728b21c1c",
      "title": "Love Thy Trillionaires",
      "summary": "Last month, Elon Musk became the first trillionaire in recorded history. A trillion requires imagination. It approaches a quarter of total US federal tax revenue. It exceeds the combined net worth of Warren Buffett, Bill Gates, and Jeff Bezos. According to Oxfam, it surpasses the total wealth of ...",
      "url": "https://www.christianitytoday.com/2026/07/love-thy-trillionaires/",
      "source_name": "Christianity Today",
      "author": "Kate Lucky",
      "topic": "marriage",
      "score": 41,
      "read_time": "1 min",
      "published_at": "2026-07-09T10:00:00+00:00",
      "scraped_at": "2026-07-12T08:00:28.337449+00:00",
      "trust_tier": 1,
      "is_live": true,
      "is_editors_pick": false,
      "time_ago": "2d ago"
    },
    {
      "id": "279a4d52be9c",
      "title": "What If You’re Missing Your Life While Waiting for It?",
      "summary": "“This isn’t the real world,” they told us. High school teachers, grumpy old men at the grocery store, cynical professors and others like them assured us throughout childhood and adolescence that our real lives were waiting somewhere in the difficult future. And while we may have not believed it w...",
      "url": "https://relevantmagazine.com/life5/life-wont-begin-your-next-milestone/",
      "source_name": "Relevant Magazine",
      "author": "cmjoyner",
      "topic": "faith",
      "score": 41,
      "read_time": "1 min",
      "published_at": "2026-07-10T13:30:00+00:00",
      "scraped_at": "2026-07-12T08:00:35.866993+00:00",
      "trust_tier": 2,
      "is_live": true,
      "is_editors_pick": false,
      "time_ago": "yesterday"
    },
    {
      "id": "2b76969337dd",
      "title": "John Cooper Shares Personal Battle That Inspired Skillet’s Powerful New Song ‘Scream’",
      "summary": "Rather than writing an angry anthem, John Cooper said Skillet's “Scream” is about choosing to fight back when life feels overwhelming.",
      "url": "https://churchleaders.com/news/2219979-john-cooper-skillet-scream-grief-betrayal-addiction-depression-illness.html",
      "source_name": "Church Leaders",
      "author": "Jesse T. Jackson",
      "topic": "faith",
      "score": 41,
      "read_time": "1 min",
      "published_at": "2026-07-10T20:45:09+00:00",
      "scraped_at": "2026-07-12T08:00:36.239341+00:00",
      "trust_tier": 2,
      "is_live": true,
      "is_editors_pick": false,
      "time_ago": "yesterday"
    },
    {
      "id": "fcd108c0f27e",
      "title": "8 Signs of a Dangerous Pastor Every Search Committee Should Know",
      "summary": "You’re on your church’s pastor search committee? Good for you. It’s a difficult task, one that can make or break your church for a long time to come. But this can be one of the finest services you render for the Lord and His church, especially if you help your church avoid dangerous pastors.",
      "url": "https://churchleaders.com/pastors/pastor-articles/170628-joe-mckeever-dangerous-pastors-that-will-destroy-your-church.html",
      "source_name": "Church Leaders",
      "author": "Joe McKeever",
      "topic": "leadership",
      "score": 41,
      "read_time": "1 min",
      "published_at": "2026-07-10T18:14:00+00:00",
      "scraped_at": "2026-07-12T08:00:36.239859+00:00",
      "trust_tier": 2,
      "is_live": true,
      "is_editors_pick": false,
      "time_ago": "yesterday"
    },
    {
      "id": "d5cc4e373f41",
      "title": "Resources of the Month: You Must Be Born Again",
      "summary": "Free eBook Resource of the Month: You Must Be Born Again by Jonathan Lair Master Being “born again” is not a cliché—it’s a matter of life or death. Writing to believers and nonbelievers alike, Jonathan Master examines Jesus’s crucial, practical teaching on total heart and life transformation. You...",
      "url": "https://churchtechtoday.com/resources-of-the-month-you-must-be-born-again/",
      "source_name": "Church Tech Today",
      "author": "CTT Staff",
      "topic": "faith",
      "score": 41,
      "read_time": "1 min",
      "published_at": "2026-07-10T11:00:00+00:00",
      "scraped_at": "2026-07-12T08:00:44.440445+00:00",
      "trust_tier": 2,
      "is_live": true,
      "is_editors_pick": false,
      "time_ago": "yesterday"
    },
    {
      "id": "92c734da9265",
      "title": "Roots & Wings FAQ: How Can We Attract More Young Families?",
      "summary": "Roots &#38; Wings: Intergenerational Formation Collaborative (R&#38;W) is a grant focused on empowering congregations to practice vibrant intergenerational liturgy, especially in Episcopal contexts. Our grant team defines intergenerational liturgy as liturgy that seeks to intentionally engage and...",
      "url": "https://buildfaith.org/roots-wings-faq-how-can-we-attract-more-young-families/",
      "source_name": "Building Faith",
      "author": "Sarah Bentley Allred (she/her/hers)",
      "topic": "leadership",
      "score": 41,
      "read_time": "1 min",
      "published_at": "2026-07-09T12:21:23+00:00",
      "scraped_at": "2026-07-12T08:00:45.836370+00:00",
      "trust_tier": 2,
      "is_live": true,
      "is_editors_pick": false,
      "time_ago": "2d ago"
    },
    {
      "id": "189df2025ea8",
      "title": "We Need a Thicker View of God’s Love",
      "summary": "All Christians would do well to have a much thicker account of the Christian life than we currently do.",
      "url": "https://www.thegospelcoalition.org/article/thicker-view-gods-love/",
      "source_name": "The Gospel Coalition",
      "author": "Kelly M. Kapic",
      "topic": "faith",
      "score": 40,
      "read_time": "1 min",
      "published_at": "2026-07-10T04:00:00+00:00",
      "scraped_at": "2026-07-12T08:00:28.212626+00:00",
      "trust_tier": 1,
      "is_live": true,
      "is_editors_pick": false,
      "time_ago": "2d ago"
    },
    {
      "id": "16d79616d93d",
      "title": "‘House of David’ Renewed for Season 3 by Prime Video",
      "summary": "Wonder Project and Amazon MGM Studios critically-acclaimed biblical drama “House of David” will return for a third season.",
      "url": "https://churchleaders.com/news/2219966-house-of-david-renewed-for-season-3-by-prime-video.html",
      "source_name": "Church Leaders",
      "author": "Jesse T. Jackson",
      "topic": "leadership",
      "score": 40,
      "read_time": "1 min",
      "published_at": "2026-07-10T19:45:43+00:00",
      "scraped_at": "2026-07-12T08:00:36.239424+00:00",
      "trust_tier": 2,
      "is_live": true,
      "is_editors_pick": false,
      "time_ago": "yesterday"
    },
    {
      "id": "63e3e0a9b903",
      "title": "7 Signs a Pharisee Spirit Is Leading Your Church",
      "summary": "How would you know if a Pharisee were running your church...or if that Pharisee were you? Here are some Pharisaical heart postures we all need to watch out for.",
      "url": "https://churchleaders.com/pastors/pastor-articles/247132-pharisee-7-signs-pharisees-running-church.html",
      "source_name": "Church Leaders",
      "author": "Carey Nieuwhof",
      "topic": "faith",
      "score": 40,
      "read_time": "1 min",
      "published_at": "2026-07-10T19:38:01+00:00",
      "scraped_at": "2026-07-12T08:00:36.239500+00:00",
      "trust_tier": 2,
      "is_live": true,
      "is_editors_pick": false,
      "time_ago": "yesterday"
    },
    {
      "id": "cb9f93270aae",
      "title": "Arizona Pastor Dale Partridge Urges ‘European Christian Colonization’ in Africa",
      "summary": "Pastor Dale Partridge listed ways the so-called curse of Ham has manifested among African peoples and cited colonization as the solution.",
      "url": "https://churchleaders.com/news/2219935-pastor-dale-partridge-european-christian-colonization-africa.html",
      "source_name": "Church Leaders",
      "author": "Stephanie Martin",
      "topic": "leadership",
      "score": 40,
      "read_time": "1 min",
      "published_at": "2026-07-10T19:34:54+00:00",
      "scraped_at": "2026-07-12T08:00:36.239585+00:00",
      "trust_tier": 2,
      "is_live": true,
      "is_editors_pick": false,
      "time_ago": "yesterday"
    },
    {
      "id": "982b7572f207",
      "title": "Former Florida Pastor Found Guilty of Drugging, Sexually Assaulting Church Member",
      "summary": "Eddy Noelsaint, a former pastor in Orlando, Florida, has been found guilty of drugging and sexually abusing a member of his congregation.",
      "url": "https://churchleaders.com/news/2219936-pastor-eddy-noelsaint-sexual-assault-church-member.html",
      "source_name": "Church Leaders",
      "author": "Dale Chamberlain",
      "topic": "leadership",
      "score": 39,
      "read_time": "1 min",
      "published_at": "2026-07-10T16:57:51+00:00",
      "scraped_at": "2026-07-12T08:00:36.239987+00:00",
      "trust_tier": 2,
      "is_live": true,
      "is_editors_pick": false,
      "time_ago": "yesterday"
    },
    {
      "id": "853984930369",
      "title": "Lecrae: ‘I Made an Idol Out of John Piper’",
      "summary": "Lecrae is opening up about one of the biggest spiritual mistakes he says he’s made: turning one of his theological heroes into an idol. On the latest episode of The Deep End, the Grammy-winning rapper reflected on his decades-long relationship with pastor and author John Piper, admitting that his...",
      "url": "https://relevantmagazine.com/faith/lecrae-i-made-an-idol-out-of-john-piper/",
      "source_name": "Relevant Magazine",
      "author": "Emily Brown",
      "topic": "leadership",
      "score": 38,
      "read_time": "1 min",
      "published_at": "2026-07-09T21:39:35+00:00",
      "scraped_at": "2026-07-12T08:00:35.867230+00:00",
      "trust_tier": 2,
      "is_live": true,
      "is_editors_pick": false,
      "time_ago": "2d ago"
    },
    {
      "id": "250697ba7dfc",
      "title": "A Kentucky Church’s VBS Skit Showed the Devil Getting Executed by Firing Squad — In Front of Kids",
      "summary": "A Kentucky church is facing backlash after a Vacation Bible School skit featuring a mock firing squad in front of children went viral online. The clip, which spread widely after being posted to Reddit, shows men in military-style clothing marching down the center aisle of Mt. Olivet Baptist Churc...",
      "url": "https://relevantmagazine.com/current/buzzworthy/a-kentucky-churchs-vbs-skit-showed-the-devil-getting-executed-by-firing-squad-in-front-of-kids/",
      "source_name": "Relevant Magazine",
      "author": "Emily Brown",
      "topic": "faith",
      "score": 38,
      "read_time": "1 min",
      "published_at": "2026-07-09T19:14:31+00:00",
      "scraped_at": "2026-07-12T08:00:35.867521+00:00",
      "trust_tier": 2,
      "is_live": true,
      "is_editors_pick": false,
      "time_ago": "2d ago"
    },
    {
      "id": "e4932135a6f9",
      "title": "‘Pray That [He] Gives His Life to Christ’—John Rich Prays With KISS Rocker Gene Simmons",
      "summary": "Country music superstar John Rich, of the duo Big &#038; Rich, recently shared that he had the opportunity to pray with iconic KISS frontman Gene Simmons.",
      "url": "https://churchleaders.com/news/2219923-john-rich-gene-simmons-gospel-pray-kiss.html",
      "source_name": "Church Leaders",
      "author": "Jesse T. Jackson",
      "topic": "faith",
      "score": 38,
      "read_time": "1 min",
      "published_at": "2026-07-10T15:32:20+00:00",
      "scraped_at": "2026-07-12T08:00:36.240089+00:00",
      "trust_tier": 2,
      "is_live": true,
      "is_editors_pick": false,
      "time_ago": "yesterday"
    },
    {
      "id": "9e125de8f016",
      "title": "Did Jesus Preach the Gospel? (TGC Classic)",
      "summary": "Did Jesus and Paul preach the same gospel?",
      "url": "https://www.thegospelcoalition.org/podcasts/tgc-podcast/did-jesus-preach-gospel-classic/",
      "source_name": "The Gospel Coalition",
      "author": "Don Carson, Kevin DeYoung, Tim Keller, John Piper",
      "topic": "faith",
      "score": 37,
      "read_time": "1 min",
      "published_at": "2026-07-10T04:04:00+00:00",
      "scraped_at": "2026-07-12T08:00:28.212474+00:00",
      "trust_tier": 1,
      "is_live": true,
      "is_editors_pick": false,
      "time_ago": "2d ago"
    },
    {
      "id": "5e9f2a6aaaf0",
      "title": "What’s the Difference Between Childlike Faith and Childish Faith?",
      "summary": "One of my clearest memories of my early childhood was sitting at the bottom of the slide on the swing set in my back yard, on an Indian Summer’s day in early September. I noticed the big yellow school bus stop outside of my neighbor’s house to drop him off from Kindergarten, and the thought&#8230;",
      "url": "https://relevantmagazine.com/faith/childlike-faith-vs-childish-faith/",
      "source_name": "Relevant Magazine",
      "author": "Brandon W. Peach",
      "topic": "faith",
      "score": 37,
      "read_time": "1 min",
      "published_at": "2026-07-09T14:00:00+00:00",
      "scraped_at": "2026-07-12T08:00:35.867620+00:00",
      "trust_tier": 2,
      "is_live": true,
      "is_editors_pick": false,
      "time_ago": "2d ago"
    },
    {
      "id": "ddf2e025ee28",
      "title": "‘Because It’s a Good Idea’—Pastor Douglas Wilson Explains to NPR Why He Wants To Repeal Women’s Right To Vote",
      "summary": "Pastor Douglas Wilson is making headlines again, this time for his position that the 19th Amendment should be repealed.",
      "url": "https://churchleaders.com/news/2219945-pastor-douglas-wilson-npr-repeal-womens-right-vote-19th-amendment.html",
      "source_name": "Church Leaders",
      "author": "Jessica Mouser",
      "topic": "leadership",
      "score": 36,
      "read_time": "1 min",
      "published_at": "2026-07-10T18:56:36+00:00",
      "scraped_at": "2026-07-12T08:00:36.239670+00:00",
      "trust_tier": 2,
      "is_live": true,
      "is_editors_pick": false,
      "time_ago": "yesterday"
    },
    {
      "id": "a2caf698ca6e",
      "title": "What Unforgiveness Does to Your Brain",
      "summary": "Unforgiveness not only keeps us chained to our offender but it profoundly affects our bodies and brains.",
      "url": "https://churchleaders.com/pastors/pastor-articles/266316-what-unforgiveness-does-to-your-brain.html",
      "source_name": "Church Leaders",
      "author": "Charles Stone",
      "topic": "faith",
      "score": 36,
      "read_time": "1 min",
      "published_at": "2026-07-10T17:39:52+00:00",
      "scraped_at": "2026-07-12T08:00:36.239921+00:00",
      "trust_tier": 2,
      "is_live": true,
      "is_editors_pick": false,
      "time_ago": "yesterday"
    },
    {
      "id": "01514b98c1e8",
      "title": "How Should Christians Think about the Law of Moses?",
      "summary": "Jesus fulfilled the law, and at the same time, he ushered in something completely new in the New Covenant. The post How Should Christians Think about the Law of Moses? appeared first on 9Marks.",
      "url": "https://www.9marks.org/review/how-should-christians-think-about-the-law-of-moses/?utm_source=rss&utm_medium=rss&utm_campaign=how-should-christians-think-about-the-law-of-moses",
      "source_name": "9Marks",
      "author": "Jeri Choi",
      "topic": "faith",
      "score": 35,
      "read_time": "1 min",
      "published_at": "2026-07-09T19:15:27+00:00",
      "scraped_at": "2026-07-12T08:00:30.192323+00:00",
      "trust_tier": 2,
      "is_live": true,
      "is_editors_pick": false,
      "time_ago": "2d ago"
    },
    {
      "id": "24f885f428c1",
      "title": "How Your Faith Changes In Your Twenties",
      "summary": "When I was 19, I remember sitting in a late-night diner with a group of friends, all of us church kids who had grown up reciting the same verses and singing the same worship songs. Someone casually admitted they weren’t sure they believed in God anymore. The table went silent. We didn’t know how ...",
      "url": "https://relevantmagazine.com/faith/5-things-ive-learned-about-faith-my-twenties-1/",
      "source_name": "Relevant Magazine",
      "author": "Zachary K. Perkins",
      "topic": "faith",
      "score": 35,
      "read_time": "1 min",
      "published_at": "2026-07-10T13:00:00+00:00",
      "scraped_at": "2026-07-12T08:00:35.867124+00:00",
      "trust_tier": 2,
      "is_live": true,
      "is_editors_pick": false,
      "time_ago": "yesterday"
    },
    {
      "id": "d7b002f38f15",
      "title": "Chinese Underground Church Leader Jin Mingri Has Been Released After Months in Prison",
      "summary": "Less than a year after Chinese authorities arrested dozens of leaders from one of the country’s largest underground churches, the pastor at the center of the crackdown is finally free. Pastor Jin Mingri, who also goes by “Ezra,” founder of Zion Church in Beijing, has been released from prison and...",
      "url": "https://relevantmagazine.com/current/world/chinese-underground-church-leader-jin-mingri-has-been-released-after-months-in-prison/",
      "source_name": "Relevant Magazine",
      "author": "Emily Brown",
      "topic": "leadership",
      "score": 34,
      "read_time": "1 min",
      "published_at": "2026-07-09T21:21:19+00:00",
      "scraped_at": "2026-07-12T08:00:35.867335+00:00",
      "trust_tier": 2,
      "is_live": true,
      "is_editors_pick": false,
      "time_ago": "2d ago"
    },
    {
      "id": "a83770a58016",
      "title": "How the Church Taught Me to Hate My Body",
      "summary": "I grew up fat and loving Jesus. I was frequently distracted and burdened by what I saw as my biggest spiritual and personal flaw: my weight. I was fat. I am fat. That has never changed. I now see the image of God reflected in my body, marveling at the way my size reveals parts&#8230;",
      "url": "https://relevantmagazine.com/life5/what-the-church-taught-me-about-being-fat/",
      "source_name": "Relevant Magazine",
      "author": "J. Nicole Morgan",
      "topic": "faith",
      "score": 34,
      "read_time": "1 min",
      "published_at": "2026-07-09T13:00:24+00:00",
      "scraped_at": "2026-07-12T08:00:35.867701+00:00",
      "trust_tier": 2,
      "is_live": true,
      "is_editors_pick": false,
      "time_ago": "2d ago"
    },
    {
      "id": "bc9622bacc87",
      "title": "Four Money Mistakes Everyone Makes (But Don’t Have to)",
      "summary": "For a lot of people, money isn&#8217;t something you really learn how to use so much as you just copy what everyone around you is doing and hope they know more than you do. That might work fine if the person you&#8217;re copying is, say, a financial planner or Jeff Bezos. But the rest of&#8230;",
      "url": "https://relevantmagazine.com/life5/career-money/4-money-mistakes-everyone-makes/",
      "source_name": "Relevant Magazine",
      "author": "John Taylor",
      "topic": "faith",
      "score": 34,
      "read_time": "1 min",
      "published_at": "2026-07-09T13:00:12+00:00",
      "scraped_at": "2026-07-12T08:00:35.867790+00:00",
      "trust_tier": 2,
      "is_live": true,
      "is_editors_pick": false,
      "time_ago": "2d ago"
    },
    {
      "id": "4206efb293ff",
      "title": "The Complete Guide to On-Demand Interpretation Services: How AI Is Replacing $200/hr Human Interpreters for Conferences, Churches, and Live Events",
      "summary": "If you have ever organized a conference, a multi-service church gathering, or a hybrid corporate event, you know the drill. Weeks before the event, you start hunting for interpreters. You negotiate rates, confirm availability, and hope nobody cancels. You pay for a minimum block of hours, even if...",
      "url": "https://churchtechtoday.com/the-complete-guide-to-on-demand-interpretation-services-how-ai-is-replacing-200-hr-human-interpreters-for-conferences-churches-and-live-events/",
      "source_name": "Church Tech Today",
      "author": "Exbabel",
      "topic": "faith",
      "score": 34,
      "read_time": "1 min",
      "published_at": "2026-07-09T13:00:00+00:00",
      "scraped_at": "2026-07-12T08:00:44.440552+00:00",
      "trust_tier": 2,
      "is_live": true,
      "is_editors_pick": false,
      "time_ago": "2d ago"
    },
    {
      "id": "fbbfcccfea66",
      "title": "Why the Church Needs to See Women in Leadership",
      "summary": "Jo Saxton: Women need leaders who can show them how to explore and engage with their call to leadership.",
      "url": "https://churchleaders.com/pastors/pastor-articles/159663-why-the-church-needs-to-see-women-in-leadership.html",
      "source_name": "Church Leaders",
      "author": "Jo Saxton",
      "topic": "leadership",
      "score": 33,
      "read_time": "1 min",
      "published_at": "2026-07-10T01:03:00+00:00",
      "scraped_at": "2026-07-12T08:00:36.240232+00:00",
      "trust_tier": 2,
      "is_live": true,
      "is_editors_pick": false,
      "time_ago": "2d ago"
    },
    {
      "id": "8a1e098a4983",
      "title": "5 of the Worst Leadership Traits I’ve Experienced",
      "summary": "A young pastor asked me a great question once. His question was this: “What are the worst leadership traits that you’ve seen limit a leader’s potential to lead well?”",
      "url": "https://churchleaders.com/pastors/455492-5-of-the-worst-leadership-traits-ive-experienced.html",
      "source_name": "Church Leaders",
      "author": "Ron Edmondson",
      "topic": "leadership",
      "score": 32,
      "read_time": "1 min",
      "published_at": "2026-07-09T20:32:55+00:00",
      "scraped_at": "2026-07-12T08:00:36.240313+00:00",
      "trust_tier": 2,
      "is_live": true,
      "is_editors_pick": false,
      "time_ago": "2d ago"
    },
    {
      "id": "85255f44d310",
      "title": "Jordan Peterson Returns to Some Work Despite Illness: ‘I’m So Relieved To Be…Doing Something Creative’",
      "summary": "Amid an extended and severe health battle, Dr. Jordan Peterson is back to writing and is also releasing weekly lectures.",
      "url": "https://churchleaders.com/news/2219898-jordan-peterson-returns-work-illness-relieved.html",
      "source_name": "Church Leaders",
      "author": "Jessica Mouser",
      "topic": "faith",
      "score": 32,
      "read_time": "1 min",
      "published_at": "2026-07-09T18:37:26+00:00",
      "scraped_at": "2026-07-12T08:00:36.240394+00:00",
      "trust_tier": 2,
      "is_live": true,
      "is_editors_pick": false,
      "time_ago": "2d ago"
    },
    {
      "id": "cc7a88bfba0e",
      "title": "Greg and Cathe Laurie Share Jesus With Beatles Legend Ringo Starr at 86th Birthday Celebration",
      "summary": "Wishing Starr a happy birthday, Cathe Laurie shared her experience on Facebook and called it a blessing to be able to talk about Jesus.",
      "url": "https://churchleaders.com/news/2219888-greg-cathe-lauire-beatles-ringo-starr.html",
      "source_name": "Church Leaders",
      "author": "Jesse T. Jackson",
      "topic": "faith",
      "score": 32,
      "read_time": "1 min",
      "published_at": "2026-07-09T16:51:30+00:00",
      "scraped_at": "2026-07-12T08:00:36.240463+00:00",
      "trust_tier": 2,
      "is_live": true,
      "is_editors_pick": false,
      "time_ago": "2d ago"
    },
    {
      "id": "1a5c6f8f74bd",
      "title": "Tim Tebow Launches Lighthouse Verticals, a New Faith-Based Microdrama Streaming Platform",
      "summary": "Philanthropist and former football star Tim Tebow is launching a new platform for faith-based microdramas.",
      "url": "https://churchleaders.com/news/2219884-tim-tebow-microdrama-streaming-platform.html",
      "source_name": "Church Leaders",
      "author": "Dale Chamberlain",
      "topic": "faith",
      "score": 32,
      "read_time": "1 min",
      "published_at": "2026-07-09T16:38:29+00:00",
      "scraped_at": "2026-07-12T08:00:36.240523+00:00",
      "trust_tier": 2,
      "is_live": true,
      "is_editors_pick": false,
      "time_ago": "2d ago"
    },
    {
      "id": "7c4fc8688759",
      "title": "7 Mistakes Pastors Make After the Altar Call",
      "summary": "Too many times, at this crucial point, perfectly normal worship services turn into \"The Phantom of the Opera.\"",
      "url": "https://churchleaders.com/pastors/preaching-teaching/246822-watch-lest-seven-mistakes-can-make-altar-call.html",
      "source_name": "Church Leaders",
      "author": "David Smith",
      "topic": "leadership",
      "score": 32,
      "read_time": "1 min",
      "published_at": "2026-07-09T15:48:00+00:00",
      "scraped_at": "2026-07-12T08:00:36.240579+00:00",
      "trust_tier": 2,
      "is_live": true,
      "is_editors_pick": false,
      "time_ago": "2d ago"
    },
    {
      "id": "4fb79dc70419",
      "title": "Bryce Crawford Says Christian Women Should Stop Affirming ‘Feminine Men’",
      "summary": "On Wednesday, evangelist Bryce Crawford posted a video on social media sharing his thoughts on “feminine men in Christianity.”",
      "url": "https://churchleaders.com/news/2219868-bryce-crawford-christian-women-affirming-feminine-men.html",
      "source_name": "Church Leaders",
      "author": "Jesse T. Jackson",
      "topic": "faith",
      "score": 32,
      "read_time": "1 min",
      "published_at": "2026-07-09T15:41:38+00:00",
      "scraped_at": "2026-07-12T08:00:36.240655+00:00",
      "trust_tier": 2,
      "is_live": true,
      "is_editors_pick": false,
      "time_ago": "2d ago"
    },
    {
      "id": "c67b2c7e04c3",
      "title": "9 Emmy Nominated Shows Worth Your Time",
      "summary": "The Emmy nominations are in, and this year&#8217;s list is genuinely good. Between a medical drama that will wreck you in the best way, a comedy that somehow gets better every season and a limited series that asks what it really means to know someone, there&#8217;s a lot worth watching before Sep...",
      "url": "https://relevantmagazine.com/culture/tv/9-emmy-nominated-shows-worth-your-time/",
      "source_name": "Relevant Magazine",
      "author": "RELEVANT",
      "topic": "faith",
      "score": 31,
      "read_time": "1 min",
      "published_at": "2026-07-09T21:21:03+00:00",
      "scraped_at": "2026-07-12T08:00:35.867420+00:00",
      "trust_tier": 2,
      "is_live": true,
      "is_editors_pick": false,
      "time_ago": "2d ago"
    },
    {
      "id": "c949f981b91a",
      "title": "Why Women Can’t Lead in Your Church",
      "summary": "In many churches and seminaries there is an underlying belief that men lead and women follow, inhibiting women leaders in the church.",
      "url": "https://churchleaders.com/pastors/pastor-articles/326863-women-leaders-in-the-church-why-women-cant-lead-in-your-church.html",
      "source_name": "Church Leaders",
      "author": "Geoff Surratt",
      "topic": "faith",
      "score": 30,
      "read_time": "1 min",
      "published_at": "2026-07-10T01:22:18+00:00",
      "scraped_at": "2026-07-12T08:00:36.240172+00:00",
      "trust_tier": 2,
      "is_live": true,
      "is_editors_pick": false,
      "time_ago": "2d ago"
    }
  ]
}